LICENSE
pywiegand/__init__.py
pywiegand/extension/pywiegand_adapter.cpp
pywiegand/extension/pywiegand_adapter.cpython-311-arm-linux-gnueabihf.so
pywiegand/extension/pywiegand_adapter.h
pywiegand-0.5.2.dist-info/LICENSE
pywiegand-0.5.2.dist-info/METADATA
pywiegand-0.5.2.dist-info/WHEEL
pywiegand-0.5.2.dist-info/RECORD
