Metadata-Version: 2.1
Name: pywiegand
Version: 0.5.2
Summary: Wiegand protocol on Raspberry PI
Home-page: https://github.com/ArPIHomeSecurity/pywiegand
License: MIT
Author: Gábor Kovács
Author-email: gkovacs81@gmail.com
Requires-Python: >=3.7,<4.0
Classifier: License :: OSI Approved :: MIT License
Classifier: Programming Language :: Python :: 3
Classifier: Programming Language :: Python :: 3.7
Classifier: Programming Language :: Python :: 3.8
Classifier: Programming Language :: Python :: 3.9
Classifier: Programming Language :: Python :: 3.10
Classifier: Programming Language :: Python :: 3.11
Project-URL: Repository, https://github.com/ArPIHomeSecurity/pywiegand
